{"expireTime":9007200835559384000,"key":"transformer-remark-markdown-html-ast-b44da5e0138ec3775d1f428a9f35eb15-gatsby-remark-custom-blocks-/SonarQubeChineseDoc8.1","val":{"type":"root","children":[{"type":"element","tagName":"h2","properties":{},"children":[{"type":"text","value":"架構（Architecture）","position":{"start":{"line":3,"column":4,"offset":5},"end":{"line":3,"column":20,"offset":21}}}],"position":{"start":{"line":3,"column":1,"offset":2},"end":{"line":3,"column":20,"offset":21}}},{"type":"text","value":"\n"},{"type":"element","tagName":"table","properties":{},"children":[{"type":"text","value":"\n"},{"type":"element","tagName":"thead","properties":{},"children":[{"type":"text","value":"\n"},{"type":"element","tagName":"tr","properties":{},"children":[{"type":"text","value":"\n"},{"type":"element","tagName":"th","properties":{"align":null},"children":[{"type":"text","value":"概念","position":{"start":{"line":4,"column":3,"offset":24},"end":{"line":4,"column":5,"offset":26}}}],"position":{"start":{"line":4,"column":3,"offset":24},"end":{"line":4,"column":6,"offset":27}}},{"type":"text","value":"\n"},{"type":"element","tagName":"th","properties":{"align":null},"children":[{"type":"text","value":"定義","position":{"start":{"line":4,"column":9,"offset":30},"end":{"line":4,"column":11,"offset":32}}}],"position":{"start":{"line":4,"column":9,"offset":30},"end":{"line":4,"column":86,"offset":107}}},{"type":"text","value":"\n"}],"position":{"start":{"line":4,"column":1,"offset":22},"end":{"line":4,"column":88,"offset":109}}},{"type":"text","value":"\n"}],"position":{"start":{"line":4,"column":1,"offset":22},"end":{"line":4,"column":88,"offset":109}}},{"type":"text","value":"\n"},{"type":"element","tagName":"tbody","properties":{},"children":[{"type":"text","value":"\n"},{"type":"element","tagName":"tr","properties":{},"children":[{"type":"text","value":"\n"},{"type":"element","tagName":"td","properties":{"align":null},"children":[{"type":"text","value":"分析儀","position":{"start":{"line":6,"column":3,"offset":213},"end":{"line":6,"column":6,"offset":216}}}],"position":{"start":{"line":6,"column":3,"offset":213},"end":{"line":6,"column":6,"offset":216}}},{"type":"text","value":"\n"},{"type":"element","tagName":"td","properties":{"align":null},"children":[{"type":"text","value":"一個分析程式碼以計算","position":{"start":{"line":6,"column":9,"offset":219},"end":{"line":6,"column":19,"offset":229}}},{"type":"element","tagName":"strong","properties":{},"children":[{"type":"text","value":"快照（snapshots）","position":{"start":{"line":6,"column":21,"offset":231},"end":{"line":6,"column":34,"offset":244}}}],"position":{"start":{"line":6,"column":19,"offset":229},"end":{"line":6,"column":36,"offset":246}}},{"type":"text","value":"的客戶端應用程式。","position":{"start":{"line":6,"column":36,"offset":246},"end":{"line":6,"column":45,"offset":255}}}],"position":{"start":{"line":6,"column":9,"offset":219},"end":{"line":6,"column":54,"offset":264}}},{"type":"text","value":"\n"}],"position":{"start":{"line":6,"column":1,"offset":211},"end":{"line":6,"column":56,"offset":266}}},{"type":"text","value":"\n"},{"type":"element","tagName":"tr","properties":{},"children":[{"type":"text","value":"\n"},{"type":"element","tagName":"td","properties":{"align":null},"children":[{"type":"text","value":"資料庫","position":{"start":{"line":7,"column":3,"offset":269},"end":{"line":7,"column":6,"offset":272}}}],"position":{"start":{"line":7,"column":3,"offset":269},"end":{"line":7,"column":6,"offset":272}}},{"type":"text","value":"\n"},{"type":"element","tagName":"td","properties":{"align":null},"children":[{"type":"text","value":"儲存組態檔（configuration）和","position":{"start":{"line":7,"column":9,"offset":275},"end":{"line":7,"column":30,"offset":296}}},{"type":"element","tagName":"strong","properties":{},"children":[{"type":"text","value":"快照（snapshots）","position":{"start":{"line":7,"column":32,"offset":298},"end":{"line":7,"column":45,"offset":311}}}],"position":{"start":{"line":7,"column":30,"offset":296},"end":{"line":7,"column":47,"offset":313}}},{"type":"text","value":"。","position":{"start":{"line":7,"column":47,"offset":313},"end":{"line":7,"column":48,"offset":314}}}],"position":{"start":{"line":7,"column":9,"offset":275},"end":{"line":7,"column":95,"offset":361}}},{"type":"text","value":"\n"}],"position":{"start":{"line":7,"column":1,"offset":267},"end":{"line":7,"column":97,"offset":363}}},{"type":"text","value":"\n"},{"type":"element","tagName":"tr","properties":{},"children":[{"type":"text","value":"\n"},{"type":"element","tagName":"td","properties":{"align":null},"children":[{"type":"text","value":"伺服器","position":{"start":{"line":8,"column":3,"offset":366},"end":{"line":8,"column":6,"offset":369}}}],"position":{"start":{"line":8,"column":3,"offset":366},"end":{"line":8,"column":8,"offset":371}}},{"type":"text","value":"\n"},{"type":"element","tagName":"td","properties":{"align":null},"children":[{"type":"text","value":"用於瀏覽","position":{"start":{"line":8,"column":11,"offset":374},"end":{"line":8,"column":15,"offset":378}}},{"type":"element","tagName":"strong","properties":{},"children":[{"type":"text","value":"快照（snapshot）","position":{"start":{"line":8,"column":17,"offset":380},"end":{"line":8,"column":29,"offset":392}}}],"position":{"start":{"line":8,"column":15,"offset":378},"end":{"line":8,"column":31,"offset":394}}},{"type":"text","value":"數據並進行組態檔（configuration）更改的 Web 介面。","position":{"start":{"line":8,"column":31,"offset":394},"end":{"line":8,"column":65,"offset":428}}}],"position":{"start":{"line":8,"column":11,"offset":374},"end":{"line":8,"column":65,"offset":428}}},{"type":"text","value":"\n"}],"position":{"start":{"line":8,"column":1,"offset":364},"end":{"line":8,"column":68,"offset":431}}},{"type":"text","value":"\n"}],"position":{"start":{"line":6,"column":1,"offset":211},"end":{"line":8,"column":68,"offset":431}}},{"type":"text","value":"\n"}],"position":{"start":{"line":4,"column":1,"offset":22},"end":{"line":8,"column":68,"offset":431}}},{"type":"text","value":"\n"},{"type":"element","tagName":"p","properties":{},"children":[{"type":"text","value":"另請參見 ","position":{"start":{"line":10,"column":1,"offset":433},"end":{"line":10,"column":6,"offset":438}}},{"type":"element","tagName":"a","properties":{"href":"/SonarQubeChineseDoc8.1/architecture/architecture-integration/"},"children":[{"type":"text","value":"SonarQube Platform Overview","position":{"start":{"line":10,"column":7,"offset":439},"end":{"line":10,"column":34,"offset":466}}}],"position":{"start":{"line":10,"column":6,"offset":438},"end":{"line":10,"column":76,"offset":508}}},{"type":"text","value":"。","position":{"start":{"line":10,"column":76,"offset":508},"end":{"line":10,"column":77,"offset":509}}}],"position":{"start":{"line":10,"column":1,"offset":433},"end":{"line":10,"column":77,"offset":509}}},{"type":"text","value":"\n"},{"type":"element","tagName":"h2","properties":{},"children":[{"type":"text","value":"品質（Quality）","position":{"start":{"line":12,"column":4,"offset":514},"end":{"line":12,"column":15,"offset":525}}}],"position":{"start":{"line":12,"column":1,"offset":511},"end":{"line":12,"column":15,"offset":525}}},{"type":"text","value":"\n"},{"type":"element","tagName":"table","properties":{},"children":[{"type":"text","value":"\n"},{"type":"element","tagName":"thead","properties":{},"children":[{"type":"text","value":"\n"},{"type":"element","tagName":"tr","properties":{},"children":[{"type":"text","value":"\n"},{"type":"element","tagName":"th","properties":{"align":null},"children":[{"type":"text","value":"概念","position":{"start":{"line":13,"column":3,"offset":528},"end":{"line":13,"column":5,"offset":530}}}],"position":{"start":{"line":13,"column":3,"offset":528},"end":{"line":13,"column":24,"offset":549}}},{"type":"text","value":"\n"},{"type":"element","tagName":"th","properties":{"align":null},"children":[{"type":"text","value":"定義","position":{"start":{"line":13,"column":27,"offset":552},"end":{"line":13,"column":29,"offset":554}}}],"position":{"start":{"line":13,"column":27,"offset":552},"end":{"line":13,"column":421,"offset":946}}},{"type":"text","value":"\n"}],"position":{"start":{"line":13,"column":1,"offset":526},"end":{"line":13,"column":423,"offset":948}}},{"type":"text","value":"\n"}],"position":{"start":{"line":13,"column":1,"offset":526},"end":{"line":13,"column":423,"offset":948}}},{"type":"text","value":"\n"},{"type":"element","tagName":"tbody","properties":{},"children":[{"type":"text","value":"\n"},{"type":"element","tagName":"tr","properties":{},"children":[{"type":"text","value":"\n"},{"type":"element","tagName":"td","properties":{"align":null},"children":[{"type":"text","value":"程式錯誤（Bug）","position":{"start":{"line":15,"column":3,"offset":1387},"end":{"line":15,"column":12,"offset":1396}}}],"position":{"start":{"line":15,"column":3,"offset":1387},"end":{"line":15,"column":35,"offset":1419}}},{"type":"text","value":"\n"},{"type":"element","tagName":"td","properties":{"align":null},"children":[{"type":"text","value":"代表程式碼中有問題。如果這個問題還沒發生，它非常可能在最壞的時機出現。這問題需要在今天解決。","position":{"start":{"line":15,"column":38,"offset":1422},"end":{"line":15,"column":84,"offset":1468}}}],"position":{"start":{"line":15,"column":38,"offset":1422},"end":{"line":15,"column":309,"offset":1693}}},{"type":"text","value":"\n"}],"position":{"start":{"line":15,"column":1,"offset":1385},"end":{"line":15,"column":311,"offset":1695}}},{"type":"text","value":"\n"},{"type":"element","tagName":"tr","properties":{},"children":[{"type":"text","value":"\n"},{"type":"element","tagName":"td","properties":{"align":null},"children":[{"type":"text","value":"代碼異味（Code Smell）","position":{"start":{"line":16,"column":3,"offset":1698},"end":{"line":16,"column":19,"offset":1714}}}],"position":{"start":{"line":16,"column":3,"offset":1698},"end":{"line":16,"column":35,"offset":1730}}},{"type":"text","value":"\n"},{"type":"element","tagName":"td","properties":{"align":null},"children":[{"type":"text","value":"程式碼中羽可維護性相關的問題。維護人員將會花費更多的時間在程式碼修改上，為了讓程式碼照著原意保留。最糟糕的是，維護人員會對程式碼的狀態感到困，以至於可能在進行修改時引入其他錯誤。","position":{"start":{"line":16,"column":38,"offset":1733},"end":{"line":16,"column":127,"offset":1822}}}],"position":{"start":{"line":16,"column":38,"offset":1733},"end":{"line":16,"column":247,"offset":1942}}},{"type":"text","value":"\n"}],"position":{"start":{"line":16,"column":1,"offset":1696},"end":{"line":16,"column":249,"offset":1944}}},{"type":"text","value":"\n"},{"type":"element","tagName":"tr","properties":{},"children":[{"type":"text","value":"\n"},{"type":"element","tagName":"td","properties":{"align":null},"children":[{"type":"text","value":"成本（Cost）","position":{"start":{"line":17,"column":3,"offset":1947},"end":{"line":17,"column":11,"offset":1955}}}],"position":{"start":{"line":17,"column":3,"offset":1947},"end":{"line":17,"column":32,"offset":1976}}},{"type":"text","value":"\n"},{"type":"element","tagName":"td","properties":{"align":null},"children":[{"type":"text","value":"請參閱修復費用","position":{"start":{"line":17,"column":35,"offset":1979},"end":{"line":17,"column":42,"offset":1986}}}],"position":{"start":{"line":17,"column":35,"offset":1979},"end":{"line":17,"column":424,"offset":2368}}},{"type":"text","value":"\n"}],"position":{"start":{"line":17,"column":1,"offset":1945},"end":{"line":17,"column":426,"offset":2370}}},{"type":"text","value":"\n"},{"type":"element","tagName":"tr","properties":{},"children":[{"type":"text","value":"\n"},{"type":"element","tagName":"td","properties":{"align":null},"children":[{"type":"text","value":"負債（Debt）","position":{"start":{"line":18,"column":3,"offset":2373},"end":{"line":18,"column":11,"offset":2381}}}],"position":{"start":{"line":18,"column":3,"offset":2373},"end":{"line":18,"column":33,"offset":2403}}},{"type":"text","value":"\n"},{"type":"element","tagName":"td","properties":{"align":null},"children":[{"type":"text","value":"請參閱技術負債（Technical Debt）","position":{"start":{"line":18,"column":36,"offset":2406},"end":{"line":18,"column":59,"offset":2429}}}],"position":{"start":{"line":18,"column":36,"offset":2406},"end":{"line":18,"column":443,"offset":2813}}},{"type":"text","value":"\n"}],"position":{"start":{"line":18,"column":1,"offset":2371},"end":{"line":18,"column":445,"offset":2815}}},{"type":"text","value":"\n"},{"type":"element","tagName":"tr","properties":{},"children":[{"type":"text","value":"\n"},{"type":"element","tagName":"td","properties":{"align":null},"children":[{"type":"text","value":"問題（Issue）","position":{"start":{"line":19,"column":3,"offset":2818},"end":{"line":19,"column":12,"offset":2827}}}],"position":{"start":{"line":19,"column":3,"offset":2818},"end":{"line":19,"column":33,"offset":2848}}},{"type":"text","value":"\n"},{"type":"element","tagName":"td","properties":{"align":null},"children":[{"type":"text","value":"如果一段程式碼不符合規則，則會在","position":{"start":{"line":19,"column":36,"offset":2851},"end":{"line":19,"column":52,"offset":2867}}},{"type":"element","tagName":"strong","properties":{},"children":[{"type":"text","value":"快照（snapshot）","position":{"start":{"line":19,"column":54,"offset":2869},"end":{"line":19,"column":66,"offset":2881}}}],"position":{"start":{"line":19,"column":52,"offset":2867},"end":{"line":19,"column":68,"offset":2883}}},{"type":"text","value":"上記錄問題。可以在原始檔案（source file）或單元測試文件（unit test file）上記錄問題。共有 3 種類型的問題：","position":{"start":{"line":19,"column":68,"offset":2883},"end":{"line":19,"column":135,"offset":2950}}},{"type":"element","tagName":"strong","properties":{},"children":[{"type":"text","value":"程式錯誤（Bugs）","position":{"start":{"line":19,"column":137,"offset":2952},"end":{"line":19,"column":147,"offset":2962}}}],"position":{"start":{"line":19,"column":135,"offset":2950},"end":{"line":19,"column":149,"offset":2964}}},{"type":"text","value":", ","position":{"start":{"line":19,"column":149,"offset":2964},"end":{"line":19,"column":151,"offset":2966}}},{"type":"element","tagName":"strong","properties":{},"children":[{"type":"text","value":"代碼異味（Code Smells）","position":{"start":{"line":19,"column":153,"offset":2968},"end":{"line":19,"column":170,"offset":2985}}}],"position":{"start":{"line":19,"column":151,"offset":2966},"end":{"line":19,"column":172,"offset":2987}}},{"type":"text","value":"和","position":{"start":{"line":19,"column":172,"offset":2987},"end":{"line":19,"column":173,"offset":2988}}},{"type":"element","tagName":"strong","properties":{},"children":[{"type":"text","value":"漏洞（Vulnerabilities）","position":{"start":{"line":19,"column":175,"offset":2990},"end":{"line":19,"column":194,"offset":3009}}}],"position":{"start":{"line":19,"column":173,"offset":2988},"end":{"line":19,"column":196,"offset":3011}}}],"position":{"start":{"line":19,"column":36,"offset":2851},"end":{"line":19,"column":359,"offset":3174}}},{"type":"text","value":"\n"}],"position":{"start":{"line":19,"column":1,"offset":2816},"end":{"line":19,"column":361,"offset":3176}}},{"type":"text","value":"\n"},{"type":"element","tagName":"tr","properties":{},"children":[{"type":"text","value":"\n"},{"type":"element","tagName":"td","properties":{"align":null},"children":[{"type":"text","value":"測量（Measure）","position":{"start":{"line":20,"column":3,"offset":3179},"end":{"line":20,"column":14,"offset":3190}}}],"position":{"start":{"line":20,"column":3,"offset":3179},"end":{"line":20,"column":33,"offset":3209}}},{"type":"text","value":"\n"},{"type":"element","tagName":"td","properties":{"align":null},"children":[{"type":"text","value":"給予文件或專案在給定時間內的","position":{"start":{"line":20,"column":36,"offset":3212},"end":{"line":20,"column":50,"offset":3226}}},{"type":"element","tagName":"strong","properties":{},"children":[{"type":"text","value":"度量（metric）","position":{"start":{"line":20,"column":52,"offset":3228},"end":{"line":20,"column":62,"offset":3238}}}],"position":{"start":{"line":20,"column":50,"offset":3226},"end":{"line":20,"column":64,"offset":3240}}},{"type":"text","value":"值。例如，MyClass 類別中的 125 行程式碼或 myProject 專案中重複的程式碼密度為 30.5％。","position":{"start":{"line":20,"column":64,"offset":3240},"end":{"line":20,"column":121,"offset":3297}}}],"position":{"start":{"line":20,"column":36,"offset":3212},"end":{"line":20,"column":346,"offset":3522}}},{"type":"text","value":"\n"}],"position":{"start":{"line":20,"column":1,"offset":3177},"end":{"line":20,"column":348,"offset":3524}}},{"type":"text","value":"\n"},{"type":"element","tagName":"tr","properties":{},"children":[{"type":"text","value":"\n"},{"type":"element","tagName":"td","properties":{"align":null},"children":[{"type":"text","value":"度量（Metric）","position":{"start":{"line":21,"column":3,"offset":3527},"end":{"line":21,"column":13,"offset":3537}}}],"position":{"start":{"line":21,"column":3,"offset":3527},"end":{"line":21,"column":33,"offset":3557}}},{"type":"text","value":"\n"},{"type":"element","tagName":"td","properties":{"align":null},"children":[{"type":"text","value":"一種測量方式。度量隨著時間的變化可以有變化的值或","position":{"start":{"line":21,"column":36,"offset":3560},"end":{"line":21,"column":60,"offset":3584}}},{"type":"element","tagName":"strong","properties":{},"children":[{"type":"text","value":"測量值（measures）","position":{"start":{"line":21,"column":62,"offset":3586},"end":{"line":21,"column":75,"offset":3599}}}],"position":{"start":{"line":21,"column":60,"offset":3584},"end":{"line":21,"column":77,"offset":3601}}},{"type":"text","value":"。舉例：程式碼行數、複雜度等。度量可以是 ","position":{"start":{"line":21,"column":77,"offset":3601},"end":{"line":21,"column":98,"offset":3622}}},{"type":"element","tagName":"em","properties":{},"children":[{"type":"text","value":"定性的（qualitative）","position":{"start":{"line":21,"column":99,"offset":3623},"end":{"line":21,"column":115,"offset":3639}}}],"position":{"start":{"line":21,"column":98,"offset":3622},"end":{"line":21,"column":116,"offset":3640}}},{"type":"text","value":"（對元件給予品質指示、重複程式碼的 EG 密度（E.G. density）或執行程式的覆蓋率等）或 ","position":{"start":{"line":21,"column":116,"offset":3640},"end":{"line":21,"column":166,"offset":3690}}},{"type":"element","tagName":"em","properties":{},"children":[{"type":"text","value":"定量的(quantitative)","position":{"start":{"line":21,"column":167,"offset":3691},"end":{"line":21,"column":184,"offset":3708}}}],"position":{"start":{"line":21,"column":166,"offset":3690},"end":{"line":21,"column":185,"offset":3709}}},{"type":"text","value":" （對元件不給予品質指示、EG 的程式碼行數、複雜度等。）","position":{"start":{"line":21,"column":185,"offset":3709},"end":{"line":21,"column":214,"offset":3738}}}],"position":{"start":{"line":21,"column":36,"offset":3560},"end":{"line":21,"column":214,"offset":3738}}},{"type":"text","value":"\n"}],"position":{"start":{"line":21,"column":1,"offset":3525},"end":{"line":21,"column":216,"offset":3740}}},{"type":"text","value":"\n"},{"type":"element","tagName":"tr","properties":{},"children":[{"type":"text","value":"\n"},{"type":"element","tagName":"td","properties":{"align":null},"children":[{"type":"text","value":"新程式碼期限（New Code Period）","position":{"start":{"line":22,"column":3,"offset":3743},"end":{"line":22,"column":26,"offset":3766}}}],"position":{"start":{"line":22,"column":3,"offset":3743},"end":{"line":22,"column":41,"offset":3781}}},{"type":"text","value":"\n"},{"type":"element","tagName":"td","properties":{"align":null},"children":[{"type":"text","value":"在這段時間內，您將密切關注程式碼中新問題的發生。理想情況下，這是從","position":{"start":{"line":22,"column":44,"offset":3784},"end":{"line":22,"column":77,"offset":3817}}},{"type":"element","tagName":"code","properties":{},"children":[{"type":"text","value":"先前版本"}],"position":{"start":{"line":22,"column":77,"offset":3817},"end":{"line":22,"column":83,"offset":3823}}},{"type":"text","value":"開始的，但是如果您不使用類似 Maven 的版本控制工具，則可能需要設定一個相對隨意的時間週期，例如 21 天或自某個特定日期開始。","position":{"start":{"line":22,"column":83,"offset":3823},"end":{"line":22,"column":149,"offset":3889}}}],"position":{"start":{"line":22,"column":44,"offset":3784},"end":{"line":22,"column":256,"offset":3996}}},{"type":"text","value":"\n"}],"position":{"start":{"line":22,"column":1,"offset":3741},"end":{"line":22,"column":258,"offset":3998}}},{"type":"text","value":"\n"},{"type":"element","tagName":"tr","properties":{},"children":[{"type":"text","value":"\n"},{"type":"element","tagName":"td","properties":{"align":null},"children":[{"type":"text","value":"品質規則組合（Quality Profile）","position":{"start":{"line":23,"column":3,"offset":4001},"end":{"line":23,"column":26,"offset":4024}}}],"position":{"start":{"line":23,"column":3,"offset":4001},"end":{"line":23,"column":37,"offset":4035}}},{"type":"text","value":"\n"},{"type":"element","tagName":"td","properties":{"align":null},"children":[{"type":"text","value":"一套","position":{"start":{"line":23,"column":40,"offset":4038},"end":{"line":23,"column":42,"offset":4040}}},{"type":"element","tagName":"strong","properties":{},"children":[{"type":"text","value":"規則（rules）","position":{"start":{"line":23,"column":44,"offset":4042},"end":{"line":23,"column":53,"offset":4051}}}],"position":{"start":{"line":23,"column":42,"offset":4040},"end":{"line":23,"column":55,"offset":4053}}},{"type":"text","value":"。每個","position":{"start":{"line":23,"column":55,"offset":4053},"end":{"line":23,"column":58,"offset":4056}}},{"type":"element","tagName":"strong","properties":{},"children":[{"type":"text","value":"快照（snapshot）","position":{"start":{"line":23,"column":60,"offset":4058},"end":{"line":23,"column":72,"offset":4070}}}],"position":{"start":{"line":23,"column":58,"offset":4056},"end":{"line":23,"column":74,"offset":4072}}},{"type":"text","value":"均基於單個品質規則組合。另請參閱 ","position":{"start":{"line":23,"column":74,"offset":4072},"end":{"line":23,"column":91,"offset":4089}}},{"type":"element","tagName":"a","properties":{"href":"/SonarQubeChineseDoc8.1/instance-administration/quality-profiles/"},"children":[{"type":"text","value":"品質規則組合（Quality Profile）","position":{"start":{"line":23,"column":92,"offset":4090},"end":{"line":23,"column":115,"offset":4113}}}],"position":{"start":{"line":23,"column":91,"offset":4089},"end":{"line":23,"column":160,"offset":4158}}}],"position":{"start":{"line":23,"column":40,"offset":4038},"end":{"line":23,"column":408,"offset":4406}}},{"type":"text","value":"\n"}],"position":{"start":{"line":23,"column":1,"offset":3999},"end":{"line":23,"column":411,"offset":4409}}},{"type":"text","value":"\n"},{"type":"element","tagName":"tr","properties":{},"children":[{"type":"text","value":"\n"},{"type":"element","tagName":"td","properties":{"align":null},"children":[{"type":"text","value":"規則（Rule）","position":{"start":{"line":24,"column":3,"offset":4412},"end":{"line":24,"column":11,"offset":4420}}}],"position":{"start":{"line":24,"column":3,"offset":4412},"end":{"line":24,"column":26,"offset":4435}}},{"type":"text","value":"\n"},{"type":"element","tagName":"td","properties":{"align":null},"children":[{"type":"text","value":"應遵循的撰寫程式碼標準或慣例。不遵守程式碼撰寫規則會導致","position":{"start":{"line":24,"column":29,"offset":4438},"end":{"line":24,"column":57,"offset":4466}}},{"type":"element","tagName":"strong","properties":{},"children":[{"type":"text","value":"程式錯誤（Bugs）","position":{"start":{"line":24,"column":59,"offset":4468},"end":{"line":24,"column":69,"offset":4478}}}],"position":{"start":{"line":24,"column":57,"offset":4466},"end":{"line":24,"column":71,"offset":4480}}},{"type":"text","value":"、","position":{"start":{"line":24,"column":71,"offset":4480},"end":{"line":24,"column":72,"offset":4481}}},{"type":"element","tagName":"strong","properties":{},"children":[{"type":"text","value":"漏洞（Vulnerabilities）","position":{"start":{"line":24,"column":74,"offset":4483},"end":{"line":24,"column":93,"offset":4502}}}],"position":{"start":{"line":24,"column":72,"offset":4481},"end":{"line":24,"column":95,"offset":4504}}},{"type":"text","value":"、","position":{"start":{"line":24,"column":95,"offset":4504},"end":{"line":24,"column":96,"offset":4505}}},{"type":"element","tagName":"strong","properties":{},"children":[{"type":"text","value":"安全熱點（Security Hotspots）","position":{"start":{"line":24,"column":98,"offset":4507},"end":{"line":24,"column":121,"offset":4530}}}],"position":{"start":{"line":24,"column":96,"offset":4505},"end":{"line":24,"column":123,"offset":4532}}},{"type":"text","value":"和","position":{"start":{"line":24,"column":123,"offset":4532},"end":{"line":24,"column":124,"offset":4533}}},{"type":"element","tagName":"strong","properties":{},"children":[{"type":"text","value":"代碼異味（Code Smells）","position":{"start":{"line":24,"column":126,"offset":4535},"end":{"line":24,"column":143,"offset":4552}}}],"position":{"start":{"line":24,"column":124,"offset":4533},"end":{"line":24,"column":145,"offset":4554}}},{"type":"text","value":"。規則可以檢查程式碼檔或單元測試的品質。","position":{"start":{"line":24,"column":145,"offset":4554},"end":{"line":24,"column":165,"offset":4574}}}],"position":{"start":{"line":24,"column":29,"offset":4438},"end":{"line":24,"column":389,"offset":4798}}},{"type":"text","value":"\n"}],"position":{"start":{"line":24,"column":1,"offset":4410},"end":{"line":24,"column":391,"offset":4800}}},{"type":"text","value":"\n"},{"type":"element","tagName":"tr","properties":{},"children":[{"type":"text","value":"\n"},{"type":"element","tagName":"td","properties":{"align":null},"children":[{"type":"text","value":"修復成本（Remediation Cost）","position":{"start":{"line":25,"column":3,"offset":4803},"end":{"line":25,"column":25,"offset":4825}}}],"position":{"start":{"line":25,"column":3,"offset":4803},"end":{"line":25,"column":35,"offset":4835}}},{"type":"text","value":"\n"},{"type":"element","tagName":"td","properties":{"align":null},"children":[{"type":"text","value":"解決漏洞和可靠性問題所需的估計時間。","position":{"start":{"line":25,"column":38,"offset":4838},"end":{"line":25,"column":56,"offset":4856}}}],"position":{"start":{"line":25,"column":38,"offset":4838},"end":{"line":25,"column":386,"offset":5186}}},{"type":"text","value":"\n"}],"position":{"start":{"line":25,"column":1,"offset":4801},"end":{"line":25,"column":388,"offset":5188}}},{"type":"text","value":"\n"},{"type":"element","tagName":"tr","properties":{},"children":[{"type":"text","value":"\n"},{"type":"element","tagName":"td","properties":{"align":null},"children":[{"type":"text","value":"快照（Snapshot）","position":{"start":{"line":26,"column":3,"offset":5191},"end":{"line":26,"column":15,"offset":5203}}}],"position":{"start":{"line":26,"column":3,"offset":5191},"end":{"line":26,"column":33,"offset":5221}}},{"type":"text","value":"\n"},{"type":"element","tagName":"td","properties":{"align":null},"children":[{"type":"text","value":"在給定時間針對給予專案的一組","position":{"start":{"line":26,"column":36,"offset":5224},"end":{"line":26,"column":50,"offset":5238}}},{"type":"element","tagName":"strong","properties":{},"children":[{"type":"text","value":"測量值（measures）","position":{"start":{"line":26,"column":52,"offset":5240},"end":{"line":26,"column":65,"offset":5253}}}],"position":{"start":{"line":26,"column":50,"offset":5238},"end":{"line":26,"column":67,"offset":5255}}},{"type":"text","value":"和","position":{"start":{"line":26,"column":67,"offset":5255},"end":{"line":26,"column":68,"offset":5256}}},{"type":"element","tagName":"strong","properties":{},"children":[{"type":"text","value":"問題（Issue）","position":{"start":{"line":26,"column":70,"offset":5258},"end":{"line":26,"column":79,"offset":5267}}}],"position":{"start":{"line":26,"column":68,"offset":5256},"end":{"line":26,"column":81,"offset":5269}}},{"type":"text","value":"。將為每個分析生成快照。","position":{"start":{"line":26,"column":81,"offset":5269},"end":{"line":26,"column":93,"offset":5281}}}],"position":{"start":{"line":26,"column":36,"offset":5224},"end":{"line":26,"column":373,"offset":5561}}},{"type":"text","value":"\n"}],"position":{"start":{"line":26,"column":1,"offset":5189},"end":{"line":26,"column":375,"offset":5563}}},{"type":"text","value":"\n"},{"type":"element","tagName":"tr","properties":{},"children":[{"type":"text","value":"\n"},{"type":"element","tagName":"td","properties":{"align":null},"children":[{"type":"text","value":"安全熱點（Security Hotspot）","position":{"start":{"line":27,"column":3,"offset":5566},"end":{"line":27,"column":25,"offset":5588}}}],"position":{"start":{"line":27,"column":3,"offset":5566},"end":{"line":27,"column":35,"offset":5598}}},{"type":"text","value":"\n"},{"type":"element","tagName":"td","properties":{"align":null},"children":[{"type":"text","value":"需要手動檢查的安全敏感程式碼片段。通過查看，您會發現沒有威脅，或者存在需要修復的易受攻擊的程式碼。","position":{"start":{"line":27,"column":38,"offset":5601},"end":{"line":27,"column":87,"offset":5650}}}],"position":{"start":{"line":27,"column":38,"offset":5601},"end":{"line":27,"column":181,"offset":5744}}},{"type":"text","value":"\n"}],"position":{"start":{"line":27,"column":1,"offset":5564},"end":{"line":27,"column":183,"offset":5746}}},{"type":"text","value":"\n"},{"type":"element","tagName":"tr","properties":{},"children":[{"type":"text","value":"\n"},{"type":"element","tagName":"td","properties":{"align":null},"children":[{"type":"text","value":"技術負債（Technical Debt）","position":{"start":{"line":28,"column":3,"offset":5749},"end":{"line":28,"column":23,"offset":5769}}}],"position":{"start":{"line":28,"column":3,"offset":5749},"end":{"line":28,"column":35,"offset":5781}}},{"type":"text","value":"\n"},{"type":"element","tagName":"td","properties":{"align":null},"children":[{"type":"text","value":"解決所有可維護性問題（Maintainability Issues）／代碼異味（code smells）所需的估計時間。","position":{"start":{"line":28,"column":38,"offset":5784},"end":{"line":28,"column":98,"offset":5844}}}],"position":{"start":{"line":28,"column":38,"offset":5784},"end":{"line":28,"column":425,"offset":6171}}},{"type":"text","value":"\n"}],"position":{"start":{"line":28,"column":1,"offset":5747},"end":{"line":28,"column":427,"offset":6173}}},{"type":"text","value":"\n"},{"type":"element","tagName":"tr","properties":{},"children":[{"type":"text","value":"\n"},{"type":"element","tagName":"td","properties":{"align":null},"children":[{"type":"text","value":"漏洞（Vulnerability）","position":{"start":{"line":29,"column":3,"offset":6176},"end":{"line":29,"column":20,"offset":6193}}}],"position":{"start":{"line":29,"column":3,"offset":6176},"end":{"line":29,"column":33,"offset":6206}}},{"type":"text","value":"\n"},{"type":"element","tagName":"td","properties":{"align":null},"children":[{"type":"text","value":"與安全相關的問題，代表攻擊者的後門。另請參閱 ","position":{"start":{"line":29,"column":36,"offset":6209},"end":{"line":29,"column":59,"offset":6232}}},{"type":"element","tagName":"a","properties":{"href":"/SonarQubeChineseDoc8.1/user-guide/security-rules/"},"children":[{"type":"text","value":"安全性相關的規則（Security-related rules）","position":{"start":{"line":29,"column":60,"offset":6233},"end":{"line":29,"column":92,"offset":6265}}}],"position":{"start":{"line":29,"column":59,"offset":6232},"end":{"line":29,"column":122,"offset":6295}}},{"type":"text","value":".","position":{"start":{"line":29,"column":122,"offset":6295},"end":{"line":29,"column":123,"offset":6296}}}],"position":{"start":{"line":29,"column":36,"offset":6209},"end":{"line":29,"column":394,"offset":6567}}},{"type":"text","value":"\n"}],"position":{"start":{"line":29,"column":1,"offset":6174},"end":{"line":29,"column":396,"offset":6569}}},{"type":"text","value":"\n"}],"position":{"start":{"line":15,"column":1,"offset":1385},"end":{"line":29,"column":396,"offset":6569}}},{"type":"text","value":"\n"}],"position":{"start":{"line":13,"column":1,"offset":526},"end":{"line":29,"column":396,"offset":6569}}}],"position":{"start":{"line":1,"column":1,"offset":0},"end":{"line":30,"column":1,"offset":6570}}}}