{"expireTime":9007200835323870000,"key":"transformer-remark-markdown-html-ast-8d48e47f1ea655637179f37a44ae3550-gatsby-remark-custom-blocks-/SonarQubeChineseDoc8.1","val":{"type":"root","children":[{"type":"element","tagName":"h2","properties":{},"children":[{"type":"text","value":"Sign up and set up your first project","position":{"start":{"line":2,"column":4,"offset":4},"end":{"line":2,"column":41,"offset":41}}}],"position":{"start":{"line":2,"column":1,"offset":1},"end":{"line":2,"column":41,"offset":41}}},{"type":"text","value":"\n"},{"type":"element","tagName":"ol","properties":{},"children":[{"type":"text","value":"\n"},{"type":"element","tagName":"li","properties":{},"children":[{"type":"text","value":"On the ","position":{"start":{"line":4,"column":4,"offset":46},"end":{"line":4,"column":11,"offset":53}}},{"type":"element","tagName":"a","properties":{"href":"/SonarQubeChineseDoc8.1/#sonarcloud#/sessions/new"},"children":[{"type":"text","value":"login page","position":{"start":{"line":4,"column":12,"offset":54},"end":{"line":4,"column":22,"offset":64}}}],"position":{"start":{"line":4,"column":11,"offset":53},"end":{"line":4,"column":51,"offset":93}}},{"type":"text","value":", click on the \"Log in with GitHub\" button and connect to SonarCloud using your GitHub account.","position":{"start":{"line":4,"column":51,"offset":93},"end":{"line":4,"column":146,"offset":188}}}],"position":{"start":{"line":4,"column":1,"offset":43},"end":{"line":4,"column":146,"offset":188}}},{"type":"text","value":"\n"},{"type":"element","tagName":"li","properties":{},"children":[{"type":"text","value":"Click on \"Analyze your code\" and follow the path to set up a first project","position":{"start":{"line":5,"column":4,"offset":192},"end":{"line":5,"column":78,"offset":266}}}],"position":{"start":{"line":5,"column":1,"offset":189},"end":{"line":5,"column":78,"offset":266}}},{"type":"text","value":"\n"},{"type":"element","tagName":"li","properties":{},"children":[{"type":"text","value":"You will be asked to install the SonarCould application on your organization, which will allow you to choose which\nrepository you want to analyze.","position":{"start":{"line":6,"column":4,"offset":270},"end":{"line":7,"column":35,"offset":419}}}],"position":{"start":{"line":6,"column":1,"offset":267},"end":{"line":7,"column":35,"offset":419}}},{"type":"text","value":"\n"}],"position":{"start":{"line":4,"column":1,"offset":43},"end":{"line":7,"column":35,"offset":419}}},{"type":"text","value":"\n"},{"type":"element","tagName":"h2","properties":{},"children":[{"type":"text","value":"Trigger analyses","position":{"start":{"line":9,"column":4,"offset":424},"end":{"line":9,"column":20,"offset":440}}}],"position":{"start":{"line":9,"column":1,"offset":421},"end":{"line":9,"column":20,"offset":440}}},{"type":"text","value":"\n"},{"type":"element","tagName":"p","properties":{},"children":[{"type":"text","value":"For GitHub repositories, there are 2 ways to have your code analyzed:","position":{"start":{"line":11,"column":1,"offset":442},"end":{"line":11,"column":70,"offset":511}}}],"position":{"start":{"line":11,"column":1,"offset":442},"end":{"line":11,"column":70,"offset":511}}},{"type":"text","value":"\n"},{"type":"element","tagName":"h3","properties":{},"children":[{"type":"text","value":"... with AutoScan","position":{"start":{"line":13,"column":5,"offset":517},"end":{"line":13,"column":22,"offset":534}}}],"position":{"start":{"line":13,"column":1,"offset":513},"end":{"line":13,"column":22,"offset":534}}},{"type":"text","value":"\n"},{"type":"element","tagName":"p","properties":{},"children":[{"type":"text","value":"With AutoScan, SonarCloud will autonomously pull your code and scan your default branch and your pull requests.\nPlease read the ","position":{"start":{"line":15,"column":1,"offset":536},"end":{"line":16,"column":17,"offset":664}}},{"type":"element","tagName":"a","properties":{"href":"/SonarQubeChineseDoc8.1/autoscan/"},"children":[{"type":"text","value":"\"AutoScan Beta Feature\"","position":{"start":{"line":16,"column":18,"offset":665},"end":{"line":16,"column":41,"offset":688}}}],"position":{"start":{"line":16,"column":17,"offset":664},"end":{"line":16,"column":54,"offset":701}}},{"type":"text","value":" documentation page to get the details.","position":{"start":{"line":16,"column":54,"offset":701},"end":{"line":16,"column":93,"offset":740}}}],"position":{"start":{"line":15,"column":1,"offset":536},"end":{"line":16,"column":93,"offset":740}}},{"type":"text","value":"\n"},{"type":"element","tagName":"div","properties":{"className":["custom-block","alert","alert-warning"]},"children":[{"type":"element","tagName":"div","properties":{"className":"custom-block-body"},"children":[{"type":"element","tagName":"p","properties":{},"children":[{"type":"text","value":"This is currently a Beta feature which does not work for all languages and comes with limitations. ","position":{"start":{"line":18,"column":1,"offset":742},"end":{"line":18,"column":100,"offset":841}}}],"position":{"start":{"line":18,"column":1,"offset":742},"end":{"line":18,"column":100,"offset":841}}}]}],"position":{"start":{"line":18,"column":1,"offset":742},"end":{"line":19,"column":102,"offset":855}}},{"type":"text","value":"\n"},{"type":"element","tagName":"h3","properties":{},"children":[{"type":"text","value":"... using your CI service","position":{"start":{"line":21,"column":5,"offset":861},"end":{"line":21,"column":30,"offset":886}}}],"position":{"start":{"line":21,"column":1,"offset":857},"end":{"line":21,"column":30,"offset":886}}},{"type":"text","value":"\n"},{"type":"element","tagName":"p","properties":{},"children":[{"type":"text","value":"If AutoScan does not make sense yet for your repository, you need to configure your CI service to trigger the analysis.","position":{"start":{"line":23,"column":1,"offset":888},"end":{"line":23,"column":120,"offset":1007}}}],"position":{"start":{"line":23,"column":1,"offset":888},"end":{"line":23,"column":120,"offset":1007}}},{"type":"text","value":"\n"},{"type":"element","tagName":"p","properties":{},"children":[{"type":"element","tagName":"strong","properties":{},"children":[{"type":"text","value":"If you are using Travis CI","position":{"start":{"line":25,"column":3,"offset":1011},"end":{"line":25,"column":29,"offset":1037}}}],"position":{"start":{"line":25,"column":1,"offset":1009},"end":{"line":25,"column":31,"offset":1039}}},{"type":"text","value":", the SonarCloud Travis Add-on will make it easier to activate analyses:","position":{"start":{"line":25,"column":31,"offset":1039},"end":{"line":25,"column":103,"offset":1111}}}],"position":{"start":{"line":25,"column":1,"offset":1009},"end":{"line":25,"column":103,"offset":1111}}},{"type":"text","value":"\n"},{"type":"element","tagName":"ul","properties":{},"children":[{"type":"text","value":"\n"},{"type":"element","tagName":"li","properties":{},"children":[{"type":"text","value":"Read the ","position":{"start":{"line":27,"column":3,"offset":1115},"end":{"line":27,"column":12,"offset":1124}}},{"type":"element","tagName":"a","properties":{"href":"https://docs.travis-ci.com/user/sonarcloud/"},"children":[{"type":"text","value":"guide to integrate with Travis CI","position":{"start":{"line":27,"column":13,"offset":1125},"end":{"line":27,"column":46,"offset":1158}}}],"position":{"start":{"line":27,"column":12,"offset":1124},"end":{"line":27,"column":92,"offset":1204}}}],"position":{"start":{"line":27,"column":1,"offset":1113},"end":{"line":27,"column":92,"offset":1204}}},{"type":"text","value":"\n"},{"type":"element","tagName":"li","properties":{},"children":[{"type":"text","value":"Check out the ","position":{"start":{"line":28,"column":3,"offset":1207},"end":{"line":28,"column":17,"offset":1221}}},{"type":"element","tagName":"a","properties":{"href":"https://github.com/SonarSource/sonarcloud_examples"},"children":[{"type":"text","value":"various sample projects","position":{"start":{"line":28,"column":18,"offset":1222},"end":{"line":28,"column":41,"offset":1245}}}],"position":{"start":{"line":28,"column":17,"offset":1221},"end":{"line":28,"column":94,"offset":1298}}},{"type":"text","value":" (Java, TypeScript, C/C++, Go, ... etc) that are analyzed on SonarCloud on a frequent basis","position":{"start":{"line":28,"column":94,"offset":1298},"end":{"line":28,"column":185,"offset":1389}}}],"position":{"start":{"line":28,"column":1,"offset":1205},"end":{"line":28,"column":185,"offset":1389}}},{"type":"text","value":"\n"}],"position":{"start":{"line":27,"column":1,"offset":1113},"end":{"line":28,"column":185,"offset":1389}}},{"type":"text","value":"\n"},{"type":"element","tagName":"p","properties":{},"children":[{"type":"element","tagName":"strong","properties":{},"children":[{"type":"text","value":"If you are using another CI service","position":{"start":{"line":30,"column":3,"offset":1393},"end":{"line":30,"column":38,"offset":1428}}}],"position":{"start":{"line":30,"column":1,"offset":1391},"end":{"line":30,"column":40,"offset":1430}}},{"type":"text","value":", you will need to read:","position":{"start":{"line":30,"column":40,"offset":1430},"end":{"line":30,"column":64,"offset":1454}}}],"position":{"start":{"line":30,"column":1,"offset":1391},"end":{"line":30,"column":64,"offset":1454}}},{"type":"text","value":"\n"},{"type":"element","tagName":"ul","properties":{},"children":[{"type":"text","value":"\n"},{"type":"element","tagName":"li","properties":{},"children":[{"type":"text","value":"the ","position":{"start":{"line":32,"column":3,"offset":1458},"end":{"line":32,"column":7,"offset":1462}}},{"type":"element","tagName":"a","properties":{"href":"/SonarQubeChineseDoc8.1/analysis/overview/"},"children":[{"type":"text","value":"\"Analyzing Source Code\" overview page","position":{"start":{"line":32,"column":8,"offset":1463},"end":{"line":32,"column":45,"offset":1500}}}],"position":{"start":{"line":32,"column":7,"offset":1462},"end":{"line":32,"column":67,"offset":1522}}}],"position":{"start":{"line":32,"column":1,"offset":1456},"end":{"line":32,"column":67,"offset":1522}}},{"type":"text","value":"\n"},{"type":"element","tagName":"li","properties":{},"children":[{"type":"text","value":"the ","position":{"start":{"line":33,"column":3,"offset":1525},"end":{"line":33,"column":7,"offset":1529}}},{"type":"element","tagName":"a","properties":{"href":"/SonarQubeChineseDoc8.1/branches/overview/"},"children":[{"type":"text","value":"\"Branches\" overview page","position":{"start":{"line":33,"column":8,"offset":1530},"end":{"line":33,"column":32,"offset":1554}}}],"position":{"start":{"line":33,"column":7,"offset":1529},"end":{"line":33,"column":54,"offset":1576}}}],"position":{"start":{"line":33,"column":1,"offset":1523},"end":{"line":33,"column":54,"offset":1576}}},{"type":"text","value":"\n"},{"type":"element","tagName":"li","properties":{},"children":[{"type":"text","value":"the ","position":{"start":{"line":34,"column":3,"offset":1579},"end":{"line":34,"column":7,"offset":1583}}},{"type":"element","tagName":"a","properties":{"href":"/SonarQubeChineseDoc8.1/analysis/pull-request/"},"children":[{"type":"text","value":"\"Pull Request Analysis\" page","position":{"start":{"line":34,"column":8,"offset":1584},"end":{"line":34,"column":36,"offset":1612}}}],"position":{"start":{"line":34,"column":7,"offset":1583},"end":{"line":34,"column":62,"offset":1638}}}],"position":{"start":{"line":34,"column":1,"offset":1577},"end":{"line":34,"column":62,"offset":1638}}},{"type":"text","value":"\n"}],"position":{"start":{"line":32,"column":1,"offset":1456},"end":{"line":34,"column":62,"offset":1638}}},{"type":"text","value":"\n"},{"type":"element","tagName":"p","properties":{},"children":[{"type":"text","value":"Here is an example of configuration for pull requests when you are not on Travis CI and you need to configure your CI jobs:","position":{"start":{"line":36,"column":1,"offset":1640},"end":{"line":36,"column":124,"offset":1763}}}],"position":{"start":{"line":36,"column":1,"offset":1640},"end":{"line":36,"column":124,"offset":1763}}},{"type":"text","value":"\n"},{"type":"element","tagName":"pre","properties":{},"children":[{"type":"element","tagName":"code","properties":{},"children":[{"type":"text","value":"sonar.pullrequest.base=master\nsonar.pullrequest.branch=feature/my-new-feature\nsonar.pullrequest.key=5\nsonar.pullrequest.provider=GitHub\nsonar.pullrequest.github.repository=my-company/my-repo\n"}],"position":{"start":{"line":37,"column":1,"offset":1764},"end":{"line":43,"column":4,"offset":1962}}}],"position":{"start":{"line":37,"column":1,"offset":1764},"end":{"line":43,"column":4,"offset":1962}}},{"type":"text","value":"\n"},{"type":"element","tagName":"div","properties":{"className":["custom-block","alert","alert-info"]},"children":[{"type":"element","tagName":"div","properties":{"className":"custom-block-body"},"children":[{"type":"element","tagName":"p","properties":{},"children":[{"type":"text","value":"Pull request decoration works only if ","position":{"start":{"line":45,"column":1,"offset":1964},"end":{"line":45,"column":39,"offset":2002}}},{"type":"element","tagName":"a","properties":{"href":"https://github.com/apps/sonarcloud"},"children":[{"type":"text","value":"the SonarCloud application","position":{"start":{"line":45,"column":40,"offset":2003},"end":{"line":45,"column":66,"offset":2029}}}],"position":{"start":{"line":45,"column":39,"offset":2002},"end":{"line":45,"column":103,"offset":2066}}},{"type":"text","value":" is installed on your GitHub organization(s) and configured to have acccess to the repositories.","position":{"start":{"line":45,"column":103,"offset":2066},"end":{"line":45,"column":199,"offset":2162}}}],"position":{"start":{"line":45,"column":1,"offset":1964},"end":{"line":45,"column":199,"offset":2162}}}]}],"position":{"start":{"line":45,"column":1,"offset":1964},"end":{"line":46,"column":201,"offset":2173}}}],"position":{"start":{"line":1,"column":1,"offset":0},"end":{"line":47,"column":1,"offset":2174}}}}